<?xml version="1.0" encoding="UTF-8"?>
<?xml-stylesheet type="text/xsl" href="default.xsl"?>
<fr:tree
toc="true"
numbered="true"
show-heading="true"
show-metadata="true"
expanded="true"
root="false"
xmlns:fr="http://www.jonmsterling.com/jms-005P.xml"><fr:frontmatter><fr:anchor>1742</fr:anchor><fr:addr
type="user">fga3.ii-a.5-proposition-5.1</fr:addr><fr:route>fga3.ii-a.5-proposition-5.1.xml</fr:route><fr:taxon>Proposition</fr:taxon><fr:authors /><fr:number>5.1</fr:number><fr:parent>fga3.ii-a.5</fr:parent></fr:frontmatter><fr:mainmatter><fr:p>Let <fr:tex
display="inline"><![CDATA[\xi \in  F(K)]]></fr:tex>, where <fr:tex
display="inline"><![CDATA[K\in \mathcal {C}]]></fr:tex> is a field.
    For the corresponding local component <fr:tex
display="inline"><![CDATA[O_\xi ]]></fr:tex> of <fr:tex
display="inline"><![CDATA[O]]></fr:tex> to be a <fr:em>Noetherian</fr:em> ring, it is necessary and sufficient that the set <fr:tex
display="inline"><![CDATA[F(I_K,\xi )]]></fr:tex> of elements of <fr:tex
display="inline"><![CDATA[F(I_K)]]></fr:tex> that are reducible along <fr:tex
display="inline"><![CDATA[\xi ]]></fr:tex> be a vector space of <fr:em>finite dimension</fr:em> over <fr:tex
display="inline"><![CDATA[K]]></fr:tex>.
    Under these conditions, we have a canonical isomorphism
    <fr:tex
display="block"><![CDATA[       F(I_K,\xi )       = \operatorname {Hom}(\mathfrak {m}_{\xi }/\mathfrak {m}_\xi ^2+\mathfrak {n}_\xi \mathscr {O}_\xi , K)     ]]></fr:tex>
    (where <fr:tex
display="inline"><![CDATA[\mathfrak {n}_\xi ]]></fr:tex> is the maximal ideal of <fr:tex
display="inline"><![CDATA[\Lambda ]]></fr:tex> given by the kernel of the homomorphism <fr:tex
display="inline"><![CDATA[\Lambda \to  K]]></fr:tex>), and so, in particular, the dimension of the <fr:tex
display="inline"><![CDATA[K]]></fr:tex>-vector space <fr:tex
display="inline"><![CDATA[F(I_K,\xi )]]></fr:tex> is equal to the dimension of the vector space <fr:tex
display="inline"><![CDATA[\mathfrak {m}_{\xi }/\mathfrak {m}_\xi ^2]]></fr:tex> over the field <fr:tex
display="inline"><![CDATA[O_{\xi }/\mathfrak {m}_\xi =K(\xi )]]></fr:tex>.</fr:p><fr:p><fr:em>[Comp.]</fr:em>
    The formula given above is only correct when <fr:tex
display="inline"><![CDATA[\Lambda ]]></fr:tex> is a field; in the general case, we must replace <fr:tex
display="inline"><![CDATA[\mathfrak {m}_{\xi }/\mathfrak {m}_\xi ^2]]></fr:tex> with the quotient of this space by the image of <fr:tex
display="inline"><![CDATA[\mathfrak {n}_{\xi }/\mathfrak {n}_\xi ^2]]></fr:tex>, where <fr:tex
display="inline"><![CDATA[\mathfrak {n}]]></fr:tex> is the maximal ideal of <fr:tex
display="inline"><![CDATA[\Lambda ]]></fr:tex>.</fr:p></fr:mainmatter><fr:backmatter><fr:tree
toc="false"
numbered="false"
show-heading="true"
show-metadata="false"
expanded="true"
root="false"
xmlns:fr="http://www.jonmsterling.com/jms-005P.xml"><fr:frontmatter><fr:title
text="Context">Context</fr:title><fr:authors /></fr:frontmatter><fr:mainmatter><fr:tree
toc="true"
numbered="false"
show-heading="true"
show-metadata="true"
expanded="false"
root="false"
xmlns:fr="http://www.jonmsterling.com/jms-005P.xml"><fr:frontmatter><fr:anchor>1743</fr:anchor><fr:addr
type="user">fga3.ii-a.5</fr:addr><fr:route>fga3.ii-a.5.xml</fr:route><fr:title
text="The existence theorem and the formal theory of modules › Representable and pro-representable functors › Example: &quot;formal varieties&quot;"><fr:link
type="local"
href="fga3.ii-a.xml"
addr="fga3.ii-a"
title="The existence theorem and the formal theory of modules › Representable and pro-representable functors"><fr:link
type="local"
href="fga3.ii.xml"
addr="fga3.ii"
title="The existence theorem and the formal theory of modules">The existence theorem and the formal theory of modules</fr:link> › Representable and pro-representable functors</fr:link> › Example: "formal varieties"</fr:title><fr:authors /><fr:number>A.5</fr:number><fr:parent>fga3.ii-a</fr:parent></fr:frontmatter><fr:mainmatter><fr:p>Let <fr:tex
display="inline"><![CDATA[\Lambda ]]></fr:tex> be a Noetherian ring, <fr:tex
display="inline"><![CDATA[\mathcal {C}]]></fr:tex> the category of <fr:tex
display="inline"><![CDATA[\Lambda ]]></fr:tex>-algebras that are Artinian modules of finite type over <fr:tex
display="inline"><![CDATA[\Lambda ]]></fr:tex> (or, more concisely, <fr:em>Artinian <fr:tex
display="inline"><![CDATA[\Lambda ]]></fr:tex>-algebras</fr:em>).
  
  The conditions of the corollary to
  <fr:ref
addr="fga3.ii-a.3-proposition-3.1"
href="fga3.ii-a.3-proposition-3.1.xml"
taxon="Proposition"
number="3.1" /> are then satisfied.
  Here, the category <fr:tex
display="inline"><![CDATA[\operatorname {Pro}(\mathcal {C})]]></fr:tex> is equivalent to the category of <fr:em>topological algebras</fr:em> <fr:tex
display="inline"><![CDATA[O]]></fr:tex> over <fr:tex
display="inline"><![CDATA[\Lambda ]]></fr:tex> that are isomorphic to topological projective limits
  <fr:tex
display="block"><![CDATA[     O     = \varprojlim  O_i   ]]></fr:tex>
  of algebras <fr:tex
display="inline"><![CDATA[O_i\in \mathcal {C}]]></fr:tex>, i.e. those whose topology is <fr:em>linear</fr:em>, <fr:em>separated</fr:em>, and <fr:em>complete</fr:em>, and such that, for every open ideal <fr:tex
display="inline"><![CDATA[\mathfrak {J}_i]]></fr:tex> of <fr:tex
display="inline"><![CDATA[O]]></fr:tex>, the algebra <fr:tex
display="inline"><![CDATA[O/\mathfrak {J}_i]]></fr:tex> is an <fr:em>Artinian</fr:em> algebra over <fr:tex
display="inline"><![CDATA[\Lambda ]]></fr:tex>.
  The functor <fr:tex
display="inline"><![CDATA[\mathcal {C}\to \mathtt {Set}]]></fr:tex> associated to such an algebra is exactly
  <fr:tex
display="block"><![CDATA[     \begin {aligned}       F(A)       &= h'_{O}(A)     \\&= \{\text {continuous homomorphisms of topological }\Lambda \text {-algebras }O\to  A\}     \\&= \varinjlim _i \operatorname {Hom}_{\Lambda \text {-algebras}}(O_i,A).     \end {aligned}   ]]></fr:tex>
  Note also that the category <fr:tex
display="inline"><![CDATA[\mathcal {C}]]></fr:tex> is essentially the product of analogous categories, corresponding to the local rings that are the completions of the <fr:tex
display="inline"><![CDATA[\Lambda _{\mathfrak {m}}]]></fr:tex> for the maximal ideals <fr:tex
display="inline"><![CDATA[\mathfrak {m}]]></fr:tex> of <fr:tex
display="inline"><![CDATA[\Lambda ]]></fr:tex>;
  we can thus, if so desired, restrict to the case where <fr:tex
display="inline"><![CDATA[A]]></fr:tex> is such a complete local ring.
  In any case, <fr:tex
display="inline"><![CDATA[O]]></fr:tex> decomposes canonically as the topological product of its <fr:em>local components</fr:em>, which correspond to the "points" of the <fr:em>formal scheme</fr:em> [<fr:ref
addr="fga2"
href="fga2.xml"
taxon="FGA"
number="2" />] defined by <fr:tex
display="inline"><![CDATA[O]]></fr:tex>.
  Such a point is defined by an object <fr:tex
display="inline"><![CDATA[\xi ]]></fr:tex> of some <fr:tex
display="inline"><![CDATA[F(K)]]></fr:tex>, where <fr:tex
display="inline"><![CDATA[K\in \mathcal {C}]]></fr:tex> is a <fr:em>field</fr:em> (for example, the residue field of the local component in question), and where two pairs <fr:tex
display="inline"><![CDATA[(\xi ,K)]]></fr:tex> and <fr:tex
display="inline"><![CDATA[(\xi ',K')]]></fr:tex> define the same point if and only if they are both dominated by the same <fr:tex
display="inline"><![CDATA[(\xi '',K'')]]></fr:tex>, or if they both dominate the same <fr:tex
display="inline"><![CDATA[(\xi ''',K''')]]></fr:tex>.
  (If the <fr:tex
display="inline"><![CDATA[{\Lambda }/\mathfrak {m}]]></fr:tex> are algebraically closed, then it suffices to take the set given by the sum of the <fr:tex
display="inline"><![CDATA[F({\Lambda }/\mathfrak {m})]]></fr:tex>).</fr:p><fr:p>It is important to give conditions that ensure that the local component <fr:tex
display="inline"><![CDATA[O_\xi ]]></fr:tex> of <fr:tex
display="inline"><![CDATA[O]]></fr:tex> corresponding to some <fr:tex
display="inline"><![CDATA[\xi \in  F(K)]]></fr:tex> be a <fr:em>Noetherian</fr:em> ring.
  If <fr:tex
display="inline"><![CDATA[\Lambda ]]></fr:tex> is a complete local ring (Noetherian, we recall), then it is equivalent to say that <fr:tex
display="inline"><![CDATA[O_\xi ]]></fr:tex> is isomorphic to a <fr:em>quotient ring of a formal series ring <fr:tex
display="inline"><![CDATA[\Lambda [{[t_1,\ldots ,t_n]}]]]></fr:tex></fr:em>.
  To give such a criterion, we introduce (for every ring <fr:tex
display="inline"><![CDATA[A]]></fr:tex>) the <fr:tex
display="inline"><![CDATA[A]]></fr:tex>-algebra <fr:tex
display="inline"><![CDATA[I_A]]></fr:tex> of "dual numbers" of <fr:tex
display="inline"><![CDATA[A]]></fr:tex>, defined by
  <fr:tex
display="block"><![CDATA[     I_A     = A[t]/t^2A[t].   ]]></fr:tex>
  Let <fr:tex
display="inline"><![CDATA[\varepsilon \colon  I_A\to  A]]></fr:tex> be the augmentation homomorphism, which defines (if <fr:tex
display="inline"><![CDATA[A\in \mathcal {C}]]></fr:tex>) a map
  <fr:tex
display="block"><![CDATA[     F(\varepsilon )\colon  F(I_A) \to  F(A).   ]]></fr:tex>
  
  Using the fact that <fr:tex
display="inline"><![CDATA[F]]></fr:tex> is left exact, we intrinsically define the structure of an <fr:tex
display="inline"><![CDATA[A]]></fr:tex>-module on the subset
  <fr:tex
display="block"><![CDATA[     F(I_A,\xi )     = F(\xi )^{-1}(\xi ) \subset  F(I_A)   ]]></fr:tex>
  consisting of the <fr:tex
display="inline"><![CDATA[\xi '\in  F(I_A)]]></fr:tex> that are "reducible along <fr:tex
display="inline"><![CDATA[\xi ]]></fr:tex>";
  using the explicit form of <fr:tex
display="inline"><![CDATA[F]]></fr:tex> in terms of <fr:tex
display="inline"><![CDATA[O]]></fr:tex>, we find that this <fr:tex
display="inline"><![CDATA[K]]></fr:tex>-module can be identified with <fr:tex
display="inline"><![CDATA[\operatorname {Hom}_\Lambda (\mathfrak {m}_{\xi }/\mathfrak {m}_\xi ^2,A)]]></fr:tex>, where <fr:tex
display="inline"><![CDATA[m_\xi ]]></fr:tex> is the kernel of the homomorphism <fr:tex
display="inline"><![CDATA[\xi \colon  O\to  A]]></fr:tex>, i.e. if <fr:tex
display="inline"><![CDATA[A]]></fr:tex> is a field, then the maximal ideal of the local component <fr:tex
display="inline"><![CDATA[O_\xi ]]></fr:tex> of <fr:tex
display="inline"><![CDATA[O]]></fr:tex>.
  From this, we immediately deduce the following proposition:</fr:p><fr:tree
toc="true"
numbered="false"
show-heading="true"
show-metadata="false"
expanded="true"
root="false"
xmlns:fr="http://www.jonmsterling.com/jms-005P.xml"><fr:frontmatter><fr:anchor>580</fr:anchor><fr:addr
type="user">fga3.ii-a.5-proposition-5.1</fr:addr><fr:route>fga3.ii-a.5-proposition-5.1.xml</fr:route><fr:taxon>Proposition</fr:taxon><fr:authors /><fr:number>5.1</fr:number><fr:parent>fga3.ii-a.5</fr:parent></fr:frontmatter><fr:mainmatter><fr:p>Let <fr:tex
display="inline"><![CDATA[\xi \in  F(K)]]></fr:tex>, where <fr:tex
display="inline"><![CDATA[K\in \mathcal {C}]]></fr:tex> is a field.
    For the corresponding local component <fr:tex
display="inline"><![CDATA[O_\xi ]]></fr:tex> of <fr:tex
display="inline"><![CDATA[O]]></fr:tex> to be a <fr:em>Noetherian</fr:em> ring, it is necessary and sufficient that the set <fr:tex
display="inline"><![CDATA[F(I_K,\xi )]]></fr:tex> of elements of <fr:tex
display="inline"><![CDATA[F(I_K)]]></fr:tex> that are reducible along <fr:tex
display="inline"><![CDATA[\xi ]]></fr:tex> be a vector space of <fr:em>finite dimension</fr:em> over <fr:tex
display="inline"><![CDATA[K]]></fr:tex>.
    Under these conditions, we have a canonical isomorphism
    <fr:tex
display="block"><![CDATA[       F(I_K,\xi )       = \operatorname {Hom}(\mathfrak {m}_{\xi }/\mathfrak {m}_\xi ^2+\mathfrak {n}_\xi \mathscr {O}_\xi , K)     ]]></fr:tex>
    (where <fr:tex
display="inline"><![CDATA[\mathfrak {n}_\xi ]]></fr:tex> is the maximal ideal of <fr:tex
display="inline"><![CDATA[\Lambda ]]></fr:tex> given by the kernel of the homomorphism <fr:tex
display="inline"><![CDATA[\Lambda \to  K]]></fr:tex>), and so, in particular, the dimension of the <fr:tex
display="inline"><![CDATA[K]]></fr:tex>-vector space <fr:tex
display="inline"><![CDATA[F(I_K,\xi )]]></fr:tex> is equal to the dimension of the vector space <fr:tex
display="inline"><![CDATA[\mathfrak {m}_{\xi }/\mathfrak {m}_\xi ^2]]></fr:tex> over the field <fr:tex
display="inline"><![CDATA[O_{\xi }/\mathfrak {m}_\xi =K(\xi )]]></fr:tex>.</fr:p><fr:p><fr:em>[Comp.]</fr:em>
    The formula given above is only correct when <fr:tex
display="inline"><![CDATA[\Lambda ]]></fr:tex> is a field; in the general case, we must replace <fr:tex
display="inline"><![CDATA[\mathfrak {m}_{\xi }/\mathfrak {m}_\xi ^2]]></fr:tex> with the quotient of this space by the image of <fr:tex
display="inline"><![CDATA[\mathfrak {n}_{\xi }/\mathfrak {n}_\xi ^2]]></fr:tex>, where <fr:tex
display="inline"><![CDATA[\mathfrak {n}]]></fr:tex> is the maximal ideal of <fr:tex
display="inline"><![CDATA[\Lambda ]]></fr:tex>.</fr:p></fr:mainmatter><fr:backmatter /></fr:tree><fr:p>Suppose that <fr:tex
display="inline"><![CDATA[O_\xi ]]></fr:tex> is Noetherian, and suppose, for notational simplicity, that <fr:tex
display="inline"><![CDATA[\Lambda ]]></fr:tex> is complete and local, and that <fr:tex
display="inline"><![CDATA[O=O_\xi ]]></fr:tex>.
  (<fr:em>[Comp.]</fr:em> The following definition is correct only when the residue extension <fr:tex
display="inline"><![CDATA[k'/k]]></fr:tex> is <fr:em>separable</fr:em>; for the general case, see [<fr:link
type="local"
href="Gro1960b.xml"
addr="Gro1960b"
title="Séminaire de Géométrie Algèbrique">Gro1960b</fr:link>, III, 1.1].)
  We say that <fr:em><fr:tex
display="inline"><![CDATA[O]]></fr:tex> is simple over <fr:tex
display="inline"><![CDATA[\Lambda ]]></fr:tex></fr:em> if <fr:tex
display="inline"><![CDATA[O]]></fr:tex> is a finite and étale algebra over the completion algebra of the localisation of <fr:tex
display="inline"><![CDATA[\Lambda [t_1,\ldots ,t_n]]]></fr:tex> at one of its maximal ideals that induces the maximal ideal of <fr:tex
display="inline"><![CDATA[\Lambda ]]></fr:tex>;
  if the residue extension of <fr:tex
display="inline"><![CDATA[O]]></fr:tex> over <fr:tex
display="inline"><![CDATA[\Lambda ]]></fr:tex> is trivial (for example, if the residue field of <fr:tex
display="inline"><![CDATA[\Lambda ]]></fr:tex> is algebraically closed), then this is equivalent to saying that <fr:tex
display="inline"><![CDATA[O]]></fr:tex> itself is isomorphic to such a formal series algebra.
  Finally, if we no longer necessarily suppose that <fr:tex
display="inline"><![CDATA[O]]></fr:tex> is Noetherian, then we again say that <fr:em><fr:tex
display="inline"><![CDATA[O]]></fr:tex> is simple over <fr:tex
display="inline"><![CDATA[\Lambda ]]></fr:tex></fr:em> if <fr:tex
display="inline"><![CDATA[O]]></fr:tex> is isomorphic to a topological projective limit of quotient <fr:tex
display="inline"><![CDATA[\Lambda ]]></fr:tex>-algebras that are Noetherian and <fr:tex
display="inline"><![CDATA[\Lambda ]]></fr:tex>-simple in the above sense.
  We can immediately generalise to the case where <fr:tex
display="inline"><![CDATA[\Lambda ]]></fr:tex> and <fr:tex
display="inline"><![CDATA[O]]></fr:tex> are no longer assumed to be local.
  With this, we have the following proposition:</fr:p><fr:tree
toc="true"
numbered="false"
show-heading="true"
show-metadata="false"
expanded="true"
root="false"
xmlns:fr="http://www.jonmsterling.com/jms-005P.xml"><fr:frontmatter><fr:anchor>581</fr:anchor><fr:addr
type="user">fga3.ii-a.5-proposition-5.2</fr:addr><fr:route>fga3.ii-a.5-proposition-5.2.xml</fr:route><fr:taxon>Proposition</fr:taxon><fr:authors /><fr:number>5.2</fr:number><fr:parent>fga3.ii-a.5</fr:parent></fr:frontmatter><fr:mainmatter><fr:p>For <fr:tex
display="inline"><![CDATA[O]]></fr:tex> to be simple over <fr:tex
display="inline"><![CDATA[\Lambda ]]></fr:tex>, it is necessary and sufficient that the associated functor <fr:tex
display="inline"><![CDATA[F]]></fr:tex> send epimorphisms to epimorphisms.</fr:p></fr:mainmatter><fr:backmatter /></fr:tree><fr:p>If this is the case, then this implies that, for every <fr:em>surjective</fr:em> homomorphism <fr:tex
display="inline"><![CDATA[A\to  A']]></fr:tex> in <fr:tex
display="inline"><![CDATA[\mathcal {C}]]></fr:tex>, the morphism <fr:tex
display="inline"><![CDATA[F(A)\to  F(A')]]></fr:tex> is also <fr:em>surjective</fr:em>.
  Of course, it suffices to verify this condition in the case where <fr:tex
display="inline"><![CDATA[A]]></fr:tex> is <fr:em>local</fr:em>, and (proceeding step-by-step) where the ideal of <fr:tex
display="inline"><![CDATA[A]]></fr:tex> given by the kernel of <fr:tex
display="inline"><![CDATA[A\to  A']]></fr:tex> is annihilated by the maximal ideal of <fr:tex
display="inline"><![CDATA[A]]></fr:tex>.
  This leads, in practice, to verifying that a certain obstruction, linked to <fr:em>infinitesimal</fr:em> invariants of the situation that give us a functor <fr:tex
display="inline"><![CDATA[F]]></fr:tex>, is null;
  this is a problem of a <fr:em>cohomological</fr:em> nature.</fr:p><fr:p>To finish, we say some words, in the above context, about <fr:em>rings of definition</fr:em>.
  Let <fr:tex
display="inline"><![CDATA[F]]></fr:tex> still be a functor from <fr:tex
display="inline"><![CDATA[\mathcal {C}]]></fr:tex> to <fr:tex
display="inline"><![CDATA[\mathtt {Set}]]></fr:tex>, assumed to be pro-representable via a topological <fr:tex
display="inline"><![CDATA[\Lambda ]]></fr:tex>-algebra <fr:tex
display="inline"><![CDATA[O]]></fr:tex>.
  Then, for every <fr:tex
display="inline"><![CDATA[A\in \mathcal {C}]]></fr:tex> and every <fr:tex
display="inline"><![CDATA[\xi \in  F(A)]]></fr:tex>, there exists a <fr:em>smallest</fr:em> subring <fr:tex
display="inline"><![CDATA[A']]></fr:tex> of <fr:tex
display="inline"><![CDATA[A]]></fr:tex> such that <fr:tex
display="inline"><![CDATA[\xi ]]></fr:tex> is the image of an element <fr:tex
display="inline"><![CDATA[\xi ']]></fr:tex> of <fr:tex
display="inline"><![CDATA[F(A')]]></fr:tex> (which is then uniquely determined):
  indeed, it suffices to think of <fr:tex
display="inline"><![CDATA[\xi ]]></fr:tex> as a homomorphism from <fr:tex
display="inline"><![CDATA[O]]></fr:tex> to <fr:tex
display="inline"><![CDATA[A]]></fr:tex>, and to take <fr:tex
display="inline"><![CDATA[A']]></fr:tex> to be the image of <fr:tex
display="inline"><![CDATA[O]]></fr:tex> under this <fr:tex
display="inline"><![CDATA[\xi ]]></fr:tex>.
  We then say that <fr:tex
display="inline"><![CDATA[A']]></fr:tex> is the <fr:em>ring of definition of the object <fr:tex
display="inline"><![CDATA[\xi \in  F(A)]]></fr:tex></fr:em>.
  If <fr:tex
display="inline"><![CDATA[u\colon  A\to  B]]></fr:tex> is an algebra homomorphism, and if <fr:tex
display="inline"><![CDATA[\eta =F(u)(\xi )]]></fr:tex>, then the ring of definition of <fr:tex
display="inline"><![CDATA[\eta ]]></fr:tex> is the image under <fr:tex
display="inline"><![CDATA[u]]></fr:tex> of the ring of definition of <fr:tex
display="inline"><![CDATA[\xi ]]></fr:tex>.
  If we start with a functor <fr:tex
display="inline"><![CDATA[F]]></fr:tex> from <fr:tex
display="inline"><![CDATA[\mathcal {C}]]></fr:tex> to <fr:tex
display="inline"><![CDATA[\mathtt {Set}]]></fr:tex>, then the existence of rings of definition, along with their properties that we have just discussed, is more or less <fr:em>equivalent</fr:em> to the condition that <fr:tex
display="inline"><![CDATA[F]]></fr:tex> be pro-representable;
  that is, they are usually far from being trivial.</fr:p></fr:mainmatter><fr:backmatter /></fr:tree></fr:mainmatter><fr:backmatter /></fr:tree><fr:tree
toc="false"
numbered="false"
show-heading="true"
show-metadata="false"
expanded="true"
root="false"
xmlns:fr="http://www.jonmsterling.com/jms-005P.xml"><fr:frontmatter><fr:title
text="Backlinks">Backlinks</fr:title><fr:authors /></fr:frontmatter><fr:mainmatter><fr:tree
toc="true"
numbered="false"
show-heading="true"
show-metadata="true"
expanded="false"
root="false"
xmlns:fr="http://www.jonmsterling.com/jms-005P.xml"><fr:frontmatter><fr:anchor>1744</fr:anchor><fr:addr
type="user">fga3.ii-c.2</fr:addr><fr:route>fga3.ii-c.2.xml</fr:route><fr:title
text="The existence theorem and the formal theory of modules › Applications to some particular cases › The schemes {{Hom}}_S(X,Y), _{X/S}Z, {{Aut}}(X), etc."><fr:link
type="local"
href="fga3.ii-c.xml"
addr="fga3.ii-c"
title="The existence theorem and the formal theory of modules › Applications to some particular cases"><fr:link
type="local"
href="fga3.ii.xml"
addr="fga3.ii"
title="The existence theorem and the formal theory of modules">The existence theorem and the formal theory of modules</fr:link> › Applications to some particular cases</fr:link> › The schemes <fr:tex
display="inline"><![CDATA[\underline {\operatorname {Hom}}_S(X,Y)]]></fr:tex>, <fr:tex
display="inline"><![CDATA[\prod _{X/S}Z]]></fr:tex>, <fr:tex
display="inline"><![CDATA[\underline {\operatorname {Aut}}(X)]]></fr:tex>, etc.</fr:title><fr:authors /><fr:number>C.2</fr:number><fr:parent>fga3.ii-c</fr:parent></fr:frontmatter><fr:mainmatter><fr:p>Let <fr:tex
display="inline"><![CDATA[X]]></fr:tex> and <fr:tex
display="inline"><![CDATA[Y]]></fr:tex> be preschemes over <fr:tex
display="inline"><![CDATA[S]]></fr:tex>;
  
  for every prescheme <fr:tex
display="inline"><![CDATA[T]]></fr:tex> over <fr:tex
display="inline"><![CDATA[S]]></fr:tex>, let <fr:tex
display="inline"><![CDATA[X_T=X\times _S T]]></fr:tex> and <fr:tex
display="inline"><![CDATA[Y_T=Y\times _S T]]></fr:tex>, and consider the set
  <fr:tex
display="block"><![CDATA[     F(T)     = \operatorname {Hom}_T(X_T,Y_T)     = \operatorname {Hom}_S(X_T,Y)     = \operatorname {Hom}_S(X\times _S T,Y)   ]]></fr:tex>
  as a contravariant functor in <fr:tex
display="inline"><![CDATA[T]]></fr:tex>.
  If it is representable, then we denote by <fr:tex
display="inline"><![CDATA[\underline {\operatorname {Hom}}_S(X,Y)]]></fr:tex> the prescheme over <fr:tex
display="inline"><![CDATA[S]]></fr:tex> that represents it, and we then have a functorial isomorphism
  <fr:tex
display="block"><![CDATA[     \operatorname {Hom}_S(T,\underline {\operatorname {Hom}}_S(X,Y)) \xrightarrow {\sim } \operatorname {Hom}_S(T\times _S X,Y).   ]]></fr:tex>
  There are variants of this universal problem, the solutions to which can be summarised as follows: a prescheme of <fr:em><fr:tex
display="inline"><![CDATA[S]]></fr:tex>-automorphisms of</fr:em> an <fr:tex
display="inline"><![CDATA[S]]></fr:tex>-prescheme <fr:tex
display="inline"><![CDATA[X]]></fr:tex> (which will be a prescheme in <fr:em>groups</fr:em>), a prescheme of <fr:em><fr:tex
display="inline"><![CDATA[S]]></fr:tex>-homomorphisms</fr:em> from an <fr:tex
display="inline"><![CDATA[S]]></fr:tex>-prescheme in <fr:em>groups</fr:em> to another (which will be a prescheme in commutative groups if the latter scheme in groups is commutative), etc.
  We can also generalise the definition of <fr:tex
display="inline"><![CDATA[\underline {\operatorname {Hom}}_S(X,Y)]]></fr:tex> by considering a prescheme <fr:tex
display="inline"><![CDATA[Z]]></fr:tex> over the prescheme <fr:tex
display="inline"><![CDATA[X]]></fr:tex> over <fr:tex
display="inline"><![CDATA[S]]></fr:tex>, and the functor
  <fr:tex
display="block"><![CDATA[     F(T)     = \operatorname {Hom}_{X_T}(X_T,Z_T)   ]]></fr:tex>
  (the set of "sections" of <fr:tex
display="inline"><![CDATA[Z_T]]></fr:tex> over <fr:tex
display="inline"><![CDATA[X_T]]></fr:tex>);
  if this functor is representable, then the <fr:tex
display="inline"><![CDATA[S]]></fr:tex>-prescheme that represents it will be denoted by <fr:tex
display="inline"><![CDATA[\Pi _{X/S}Z]]></fr:tex>, and we will thus have, by definition, a functorial isomorphism
  <fr:tex
display="block"><![CDATA[     \operatorname {Hom}_S(T,\Pi _{X/S}Z)     = \operatorname {Hom}_{X_T}(X_T,Z_T).   ]]></fr:tex>
  Setting <fr:tex
display="inline"><![CDATA[Z=Y\times _S X]]></fr:tex>, we recover <fr:tex
display="inline"><![CDATA[\underline {\operatorname {Hom}}_S(X,Y)]]></fr:tex>.
  From these definitions follows a formula for the new preschemes thus introduced that is as trivial as it is useful, that we will not give here (given that it holds in every category where products and fibred products exist).
  More serious is the question of <fr:em>existence</fr:em> of schemes of the type <fr:tex
display="inline"><![CDATA[\underline {\operatorname {Hom}}_S(X,Y)]]></fr:tex>.
  We note first of all that, for fixed <fr:tex
display="inline"><![CDATA[X]]></fr:tex>, <fr:tex
display="inline"><![CDATA[\underline {\operatorname {Hom}}_S(X,Y)]]></fr:tex> (resp. <fr:tex
display="inline"><![CDATA[\Pi _{X/S}Z]]></fr:tex>) can only exist for all <fr:tex
display="inline"><![CDATA[Y]]></fr:tex> over <fr:tex
display="inline"><![CDATA[S]]></fr:tex> (resp. for all <fr:tex
display="inline"><![CDATA[Z]]></fr:tex> over <fr:tex
display="inline"><![CDATA[X]]></fr:tex>) if <fr:tex
display="inline"><![CDATA[X]]></fr:tex> is <fr:em>flat</fr:em> over <fr:tex
display="inline"><![CDATA[S]]></fr:tex>.
  Furthermore, we can convince ourselves that it is not reasonable to expect the existence of a solution, for general enough <fr:tex
display="inline"><![CDATA[Y]]></fr:tex>, except in the case where <fr:tex
display="inline"><![CDATA[X]]></fr:tex> is further <fr:em>proper</fr:em> over <fr:tex
display="inline"><![CDATA[S]]></fr:tex>.
  It seems, however, that these conditions are sufficient for the existence of <fr:tex
display="inline"><![CDATA[\underline {\operatorname {Hom}}_S(X,Y)]]></fr:tex> and <fr:tex
display="inline"><![CDATA[\Pi _{X/S}Z]]></fr:tex>, with the condition that, if necessary, we make some sort of "quasi-projective" hypothesis on <fr:tex
display="inline"><![CDATA[Y/S]]></fr:tex> (resp. <fr:tex
display="inline"><![CDATA[Z/X]]></fr:tex>);
  this is what we can verify anyway in numerous cases (for example, when <fr:tex
display="inline"><![CDATA[Y]]></fr:tex> is <fr:em>affine</fr:em> over <fr:tex
display="inline"><![CDATA[S]]></fr:tex>, or, by direct elementary constructions, when <fr:tex
display="inline"><![CDATA[X]]></fr:tex> is <fr:em>finite</fr:em> over <fr:tex
display="inline"><![CDATA[S]]></fr:tex>).
  Then <fr:ref
addr="fga3.ii-b-theorem-1"
href="fga3.ii-b-theorem-1.xml"
taxon="Theorem"
number="1" /> and <fr:ref
addr="fga3.ii-b-theorem-2"
href="fga3.ii-b-theorem-2.xml"
taxon="Theorem"
number="2" /> give:</fr:p><fr:tree
toc="true"
numbered="false"
show-heading="true"
show-metadata="false"
expanded="true"
root="false"
xmlns:fr="http://www.jonmsterling.com/jms-005P.xml"><fr:frontmatter><fr:anchor>1745</fr:anchor><fr:addr
type="user">fga3.ii-c.2-proposition-2.1</fr:addr><fr:route>fga3.ii-c.2-proposition-2.1.xml</fr:route><fr:taxon>Proposition</fr:taxon><fr:authors /><fr:number>2.1</fr:number><fr:parent>fga3.ii-c.2</fr:parent></fr:frontmatter><fr:mainmatter><fr:p>Let <fr:tex
display="inline"><![CDATA[\Lambda ]]></fr:tex> be a Noetherian ring, and <fr:tex
display="inline"><![CDATA[X]]></fr:tex> and <fr:tex
display="inline"><![CDATA[Y]]></fr:tex> arbitrary preschemes over <fr:tex
display="inline"><![CDATA[\Lambda ]]></fr:tex>.
    Consider the functor
    <fr:tex
display="block"><![CDATA[       F(A)       = \operatorname {Hom}_A(X_A,Y_A)     ]]></fr:tex>
    on the category <fr:tex
display="inline"><![CDATA[\mathcal {C}_0]]></fr:tex> of Artinian <fr:tex
display="inline"><![CDATA[\Lambda ]]></fr:tex>-algebras.
    If <fr:tex
display="inline"><![CDATA[X]]></fr:tex> is flat over <fr:tex
display="inline"><![CDATA[\Lambda ]]></fr:tex>, then this functor is pro-representable.</fr:p></fr:mainmatter><fr:backmatter /></fr:tree><fr:p>Furthermore, we can show that, for all <fr:tex
display="inline"><![CDATA[A\in \mathcal {C}_0]]></fr:tex> and all <fr:tex
display="inline"><![CDATA[\xi \in  F(A)]]></fr:tex>, we have a canonical isomorphism
  <fr:tex
display="block"><![CDATA[     F(I_A,\xi )     = \operatorname {H}^1\Big (X_A,\underline {\operatorname {Hom}}_{\mathscr {O}_{X_A}}\big (\xi ^*(\Omega _{Y_A/A}^1),\mathscr {O}_{X_A}\big )\Big )   ]]></fr:tex>
  where <fr:tex
display="inline"><![CDATA[\Omega _{Y_A/A}^1]]></fr:tex> is the sheaf of Kähler <fr:tex
display="inline"><![CDATA[1]]></fr:tex>-differentials of <fr:tex
display="inline"><![CDATA[Y_A]]></fr:tex> with respect to <fr:tex
display="inline"><![CDATA[A]]></fr:tex>.
  Taking <fr:tex
display="inline"><![CDATA[A]]></fr:tex> to be a field, we find, using <fr:link
type="local"
href="fga3.ii-a.5-proposition-5.1.xml"
addr="fga3.ii-a.5-proposition-5.1">§A, Proposition 5.1</fr:link> and the finiteness theorem from <fr:ref
addr="fga2"
href="fga2.xml"
taxon="FGA"
number="2" />, the following corollary:</fr:p><fr:tree
toc="true"
numbered="false"
show-heading="true"
show-metadata="false"
expanded="true"
root="false"
xmlns:fr="http://www.jonmsterling.com/jms-005P.xml"><fr:frontmatter><fr:anchor>1746</fr:anchor><fr:addr
type="user">fga3.ii-c.2-proposition-2.1-corollary</fr:addr><fr:route>fga3.ii-c.2-proposition-2.1-corollary.xml</fr:route><fr:taxon>Corollary</fr:taxon><fr:authors /><fr:parent>fga3.ii-c.2</fr:parent></fr:frontmatter><fr:mainmatter><fr:p>Suppose that <fr:tex
display="inline"><![CDATA[X]]></fr:tex> is flat and proper over <fr:tex
display="inline"><![CDATA[S]]></fr:tex>, and that <fr:tex
display="inline"><![CDATA[Y]]></fr:tex> is of finite type over <fr:tex
display="inline"><![CDATA[S]]></fr:tex>.
    Then <fr:tex
display="inline"><![CDATA[F]]></fr:tex> is pro-representable, and the local components of the corresponding topological <fr:tex
display="inline"><![CDATA[\Lambda ]]></fr:tex>-algebra are <fr:em>Noetherian</fr:em> rings.</fr:p></fr:mainmatter><fr:backmatter /></fr:tree><fr:tree
toc="true"
numbered="false"
show-heading="true"
show-metadata="false"
expanded="true"
root="false"
xmlns:fr="http://www.jonmsterling.com/jms-005P.xml"><fr:frontmatter><fr:anchor>1747</fr:anchor><fr:addr
type="user">fga3.ii-c.2-remarks</fr:addr><fr:route>fga3.ii-c.2-remarks.xml</fr:route><fr:taxon>Remarks</fr:taxon><fr:authors /><fr:parent>fga3.ii-c.2</fr:parent></fr:frontmatter><fr:mainmatter><fr:p>The problems considered in this section, and many others, having been generally studied, in the framework of classical algebraic geometry, via the "Chow coordinates" of cycles in projective space, allow us to consider these cycles as points of suitable projective varieties.
    This procedure, and, more generally, the use of Chow coordinates, seems irredeemably insufficient from the point of view of schemes, since it destroys the nilpotent elements in the parameterised varieties, and, in particular, do not lend themselves to a satisfying study of infinitesimal variations of cycles (without taking its non-intrinsic nature, linked to the projective space, into account).
    The language of Chow coordinates has sadly been the only one used by many algebraic geometers for the study of families of varieties or families of cycles, which seems to have been a serious obstacle to the understanding of these notions, despite its certain technical interest (probably temporary).
    If we wish to obtain the analogue of Chow varieties in the theory of schemes, we are led to the following universal problem:
    let <fr:tex
display="inline"><![CDATA[X]]></fr:tex> be a prescheme over <fr:tex
display="inline"><![CDATA[S]]></fr:tex>, and, for every prescheme <fr:tex
display="inline"><![CDATA[T]]></fr:tex> over <fr:tex
display="inline"><![CDATA[S]]></fr:tex>, consider the set <fr:tex
display="inline"><![CDATA[F(T)]]></fr:tex> of closed sub-preschemes of <fr:tex
display="inline"><![CDATA[X_T=X\times _S T]]></fr:tex> that are <fr:em>flat</fr:em> over <fr:tex
display="inline"><![CDATA[T]]></fr:tex>; we want to represent this functor in <fr:tex
display="inline"><![CDATA[T]]></fr:tex> via some prescheme over <fr:tex
display="inline"><![CDATA[S]]></fr:tex>.
    
    More generally, we can start with a quasi-coherent sheaf <fr:tex
display="inline"><![CDATA[\mathscr {G}]]></fr:tex> on <fr:tex
display="inline"><![CDATA[X]]></fr:tex>, and take <fr:tex
display="inline"><![CDATA[F(T)]]></fr:tex> to be the set of quotient sheaves of <fr:tex
display="inline"><![CDATA[\mathscr {G}_T]]></fr:tex> that are flat over <fr:tex
display="inline"><![CDATA[T]]></fr:tex>.
    It seems that there exists a solution to this problem, with a scheme <fr:tex
display="inline"><![CDATA[C]]></fr:tex> that is locally of finite type over <fr:tex
display="inline"><![CDATA[S]]></fr:tex>, if <fr:tex
display="inline"><![CDATA[X]]></fr:tex> is proper over <fr:tex
display="inline"><![CDATA[S]]></fr:tex>, if <fr:tex
display="inline"><![CDATA[S]]></fr:tex> is locally Noetherian, and if <fr:tex
display="inline"><![CDATA[F]]></fr:tex> is furthermore coherent.
    In any case, supposing only that <fr:tex
display="inline"><![CDATA[S]]></fr:tex> is locally Noetherian, the restriction of <fr:tex
display="inline"><![CDATA[F]]></fr:tex> to "Artinian <fr:tex
display="inline"><![CDATA[S]]></fr:tex>-algebras" is pro-representable, and, if, furthermore, <fr:tex
display="inline"><![CDATA[X]]></fr:tex> is proper over <fr:tex
display="inline"><![CDATA[S]]></fr:tex>, and <fr:tex
display="inline"><![CDATA[F]]></fr:tex> is coherent, then the local components of the corresponding topological ring <fr:tex
display="inline"><![CDATA[\mathscr {O}]]></fr:tex> are Noetherian.
    Of course, even after having proven the existence of the "Chow scheme" of <fr:tex
display="inline"><![CDATA[X]]></fr:tex> over <fr:tex
display="inline"><![CDATA[S]]></fr:tex>, it remains to find a decomposition of it into disjoint open subsets <fr:tex
display="inline"><![CDATA[C_i]]></fr:tex> (corresponding to fixing continuous invariants, such as degree and dimension of the cycles that we vary) over <fr:tex
display="inline"><![CDATA[S]]></fr:tex>, as well as to make precise the relations between this scheme with the classical Chow varieties, and to make precise when a <fr:tex
display="inline"><![CDATA[C_i]]></fr:tex> is <fr:em>projective</fr:em> (or at least quasi-projective) over <fr:tex
display="inline"><![CDATA[S]]></fr:tex>.</fr:p></fr:mainmatter><fr:backmatter /></fr:tree><fr:tree
toc="true"
numbered="false"
show-heading="true"
show-metadata="false"
expanded="true"
root="false"
xmlns:fr="http://www.jonmsterling.com/jms-005P.xml"><fr:frontmatter><fr:anchor>1748</fr:anchor><fr:addr
type="user">fga3.ii-c.2-remark</fr:addr><fr:route>fga3.ii-c.2-remark.xml</fr:route><fr:taxon>Remark</fr:taxon><fr:authors /><fr:parent>fga3.ii-c.2</fr:parent></fr:frontmatter><fr:mainmatter><fr:p><fr:em>[Comp.]</fr:em>
    The problems described here are completely resolved in the projective case by "Hilbert schemes" (cf. <fr:ref
addr="fga3.iv"
href="fga3.iv.xml"
taxon="FGA"
number="3.IV" />).
    Examples by Nagata and Hironaka show, however, that the functors described are not necessarily representable if we do not make the projective hypothesis, even if we restrict to the classification of subvarieties of dimension <fr:tex
display="inline"><![CDATA[0]]></fr:tex> of a complete non-singular variety of dimension <fr:tex
display="inline"><![CDATA[3]]></fr:tex>;
    this is linked to the fact that the symmetric square of such a variety does not necessarily exist.</fr:p></fr:mainmatter><fr:backmatter /></fr:tree></fr:mainmatter><fr:backmatter /></fr:tree></fr:mainmatter><fr:backmatter /></fr:tree></fr:backmatter></fr:tree>